setup.py
Pyternion.egg-info/PKG-INFO
Pyternion.egg-info/SOURCES.txt
Pyternion.egg-info/dependency_links.txt
Pyternion.egg-info/top_level.txt
pyternion/__init__.py