Metadata-Version: 1.0
Name: Pyternion
Version: 1.0
Summary: Pythonic Quaternion library including Euclidean geometry calculations
Home-page: UNKNOWN
Author: Philip Peterson
Author-email: philip.c.peterson@gmail.com
License: UNKNOWN
Platform: UNKNOWN
